llyfrau/__init__.py
llyfrau/__main__.py
llyfrau/_version.py
llyfrau/data.py
llyfrau/importers.py
llyfrau/cli/__init__.py
llyfrau/cli/tui.py
llyfrau-0.3.0.dist-info/LICENSE
llyfrau-0.3.0.dist-info/METADATA
llyfrau-0.3.0.dist-info/WHEEL
llyfrau-0.3.0.dist-info/entry_points.txt
llyfrau-0.3.0.dist-info/top_level.txt
llyfrau-0.3.0.dist-info/RECORD
